dictconf/__init__.py
dictconf/lib.py
dictconf-0.1.0.dist-info/METADATA
dictconf-0.1.0.dist-info/WHEEL
dictconf-0.1.0.dist-info/top_level.txt
dictconf-0.1.0.dist-info/RECORD
