Metadata-Version: 2.4
Name: dictconf
Version: 0.1.0
Summary: A simple, file-composition-based configuration library.
Author-email: Philip Hierhager <philip.hierhager@googlemail.com>
License: MIT License
Project-URL: Homepage, https://github.com/user/dictconf
Classifier: Programming Language :: Python :: 3
Classifier: License :: OSI Approved :: MIT License
Classifier: Operating System :: OS Independent
Requires-Python: >=3.8
Requires-Dist: PyYAML>=6.0
Provides-Extra: dacite
Requires-Dist: dacite>=1.8.0; extra == "dacite"
Provides-Extra: dev
Requires-Dist: pytest>=7.0; extra == "dev"
Requires-Dist: pytest-cov>=4.0; extra == "dev"
Requires-Dist: ruff>=0.1.0; extra == "dev"
Requires-Dist: mypy>=1.5.0; extra == "dev"
Requires-Dist: build; extra == "dev"
Requires-Dist: twine; extra == "dev"
